clotion/__init__.py
clotion/config.py
clotion/main.py
clotion/claude/__init__.py
clotion/claude/activity.py
clotion/claude/hooks.py
clotion/claude/runner.py
clotion/git/__init__.py
clotion/git/github.py
clotion/git/worktree.py
clotion/notion/__init__.py
clotion/notion/client.py
clotion/notion/poller.py
clotion/notion/properties.py
clotion/tasks/__init__.py
clotion/tasks/manager.py
clotion/tasks/state.py
clotion/tasks/store.py
clotion-0.1.0.dist-info/METADATA
clotion-0.1.0.dist-info/WHEEL
clotion-0.1.0.dist-info/entry_points.txt
clotion-0.1.0.dist-info/RECORD
