Metadata-Version: 2.4
Name: clotion
Version: 0.1.0
Summary: Autonomous development automation with Claude Code and Notion
Requires-Python: >=3.9
Requires-Dist: aiosqlite>=0.19.0
Requires-Dist: httpx>=0.26.0
Requires-Dist: pydantic-settings>=2.1.0
Requires-Dist: pydantic>=2.5.0
Requires-Dist: python-dotenv>=1.0.0
Provides-Extra: dev
Requires-Dist: black>=23.12.0; extra == 'dev'
Requires-Dist: pytest-asyncio>=0.23.0; extra == 'dev'
Requires-Dist: pytest>=7.4.0; extra == 'dev'
Requires-Dist: ruff>=0.1.9; extra == 'dev'
